[
    {
        "pagePath": "/trilhas/",
        "year": "2025",
        "month": "04",
        "activeUsers": "2450",
        "screenPageViews": "2893",
        "screenPageViewsPerSession": "1.109704641350211",
        "screenPageViewPerUser": "1.1808163265306122",
        "averageSessionDuration": "46.908416273878025",
        "bounceRate": "0.38856923667050247"
    },
    {
        "pagePath": "/trilhas/python/",
        "year": "2025",
        "month": "04",
        "activeUsers": "785",
        "screenPageViews": "1067",
        "screenPageViewsPerSession": "1.2552941176470589",
        "screenPageViewPerUser": "1.3592356687898088",
        "averageSessionDuration": "87.799216547058833",
        "bounceRate": "0.0611764705882353"
    },
    {
        "pagePath": "/trilhas/python/page-1/",
        "year": "2025",
        "month": "04",
        "activeUsers": "274",
        "screenPageViews": "414",
        "screenPageViewsPerSession": "1.3354838709677419",
        "screenPageViewPerUser": "1.5109489051094891",
        "averageSessionDuration": "117.49873680322581",
        "bounceRate": "0.0935483870967742"
    },
    {
        "pagePath": "/projetos/",
        "year": "2025",
        "month": "04",
        "activeUsers": "249",
        "screenPageViews": "292",
        "screenPageViewsPerSession": "1.0814814814814815",
        "screenPageViewPerUser": "1.1726907630522088",
        "averageSessionDuration": "46.326788292592596",
        "bounceRate": "0.048148148148148148"
    },
    {
        "pagePath": "/quero/estudar/",
        "year": "2025",
        "month": "04",
        "activeUsers": "185",
        "screenPageViews": "240",
        "screenPageViewsPerSession": "1.2",
        "screenPageViewPerUser": "1.2972972972972974",
        "averageSessionDuration": "65.96895337",
        "bounceRate": "0.06"
    },
    {
        "pagePath": "/trilhas/python/page-2/",
        "year": "2025",
        "month": "04",
        "activeUsers": "165",
        "screenPageViews": "254",
        "screenPageViewsPerSession": "1.3956043956043955",
        "screenPageViewPerUser": "1.5393939393939393",
        "averageSessionDuration": "89.562317934065945",
        "bounceRate": "0.071428571428571425"
    },
    {
        "pagePath": "/trilhas/github/",
        "year": "2025",
        "month": "04",
        "activeUsers": "130",
        "screenPageViews": "155",
        "screenPageViewsPerSession": "1.1071428571428572",
        "screenPageViewPerUser": "1.1923076923076923",
        "averageSessionDuration": "26.996323235714286",
        "bounceRate": "0.035714285714285712"
    },
    {
        "pagePath": "/team/",
        "year": "2025",
        "month": "04",
        "activeUsers": "94",
        "screenPageViews": "122",
        "screenPageViewsPerSession": "1.1192660550458715",
        "screenPageViewPerUser": "1.2978723404255319",
        "averageSessionDuration": "18.594949532110093",
        "bounceRate": "0.11009174311926606"
    },
    {
        "pagePath": "/trilhas/python/page-3/",
        "year": "2025",
        "month": "04",
        "activeUsers": "89",
        "screenPageViews": "141",
        "screenPageViewsPerSession": "1.0930232558139534",
        "screenPageViewPerUser": "1.5842696629213484",
        "averageSessionDuration": "45.847226953488374",
        "bounceRate": "0.31007751937984496"
    },
    {
        "pagePath": "/trilhas/github/page-1/",
        "year": "2025",
        "month": "04",
        "activeUsers": "69",
        "screenPageViews": "81",
        "screenPageViewsPerSession": "1.1095890410958904",
        "screenPageViewPerUser": "1.173913043478261",
        "averageSessionDuration": "87.319820616438378",
        "bounceRate": "0.0547945205479452"
    },
    {
        "pagePath": "/trilhas/python/page-4/",
        "year": "2025",
        "month": "04",
        "activeUsers": "58",
        "screenPageViews": "83",
        "screenPageViewsPerSession": "1.2205882352941178",
        "screenPageViewPerUser": "1.4310344827586208",
        "averageSessionDuration": "108.21606297058823",
        "bounceRate": "0.073529411764705885"
    },
    {
        "pagePath": "/trilhas/python/page-5/",
        "year": "2025",
        "month": "04",
        "activeUsers": "54",
        "screenPageViews": "67",
        "screenPageViewsPerSession": "1.1166666666666667",
        "screenPageViewPerUser": "1.2407407407407407",
        "averageSessionDuration": "115.62742739999999",
        "bounceRate": "0.066666666666666666"
    },
    {
        "pagePath": "/quero/mentoria/",
        "year": "2025",
        "month": "04",
        "activeUsers": "50",
        "screenPageViews": "74",
        "screenPageViewsPerSession": "1.1212121212121211",
        "screenPageViewPerUser": "1.48",
        "averageSessionDuration": "150.33426212121213",
        "bounceRate": "0.19696969696969696"
    },
    {
        "pagePath": "/trilhas/github/page-2/",
        "year": "2025",
        "month": "04",
        "activeUsers": "48",
        "screenPageViews": "53",
        "screenPageViewsPerSession": "1.0816326530612246",
        "screenPageViewPerUser": "1.1041666666666667",
        "averageSessionDuration": "114.58496889795921",
        "bounceRate": "0.020408163265306121"
    },
    {
        "pagePath": "/trilhas/python/page-9/",
        "year": "2025",
        "month": "04",
        "activeUsers": "36",
        "screenPageViews": "41",
        "screenPageViewsPerSession": "1.1388888888888888",
        "screenPageViewPerUser": "1.1388888888888888",
        "averageSessionDuration": "39.60109352777777",
        "bounceRate": "0"
    },
    {
        "pagePath": "/trilhas/python/page-10/",
        "year": "2025",
        "month": "04",
        "activeUsers": "34",
        "screenPageViews": "40",
        "screenPageViewsPerSession": "1.0810810810810811",
        "screenPageViewPerUser": "1.1764705882352942",
        "averageSessionDuration": "112.141247",
        "bounceRate": "0.054054054054054057"
    },
    {
        "pagePath": "/trilhas/python/page-8/",
        "year": "2025",
        "month": "04",
        "activeUsers": "34",
        "screenPageViews": "37",
        "screenPageViewsPerSession": "1.088235294117647",
        "screenPageViewPerUser": "1.088235294117647",
        "averageSessionDuration": "59.9565965882353",
        "bounceRate": "0"
    },
    {
        "pagePath": "/trilhas/github/page-3/",
        "year": "2025",
        "month": "04",
        "activeUsers": "30",
        "screenPageViews": "38",
        "screenPageViewsPerSession": "0.95",
        "screenPageViewPerUser": "1.2666666666666666",
        "averageSessionDuration": "112.12765145",
        "bounceRate": "0.25"
    },
    {
        "pagePath": "/trilhas/python/page-15/",
        "year": "2025",
        "month": "04",
        "activeUsers": "30",
        "screenPageViews": "32",
        "screenPageViewsPerSession": "1.032258064516129",
        "screenPageViewPerUser": "1.0666666666666667",
        "averageSessionDuration": "57.569266516129034",
        "bounceRate": "0"
    },
    {
        "pagePath": "/trilhas/github/page-5/",
        "year": "2025",
        "month": "04",
        "activeUsers": "29",
        "screenPageViews": "38",
        "screenPageViewsPerSession": "1.2258064516129032",
        "screenPageViewPerUser": "1.3103448275862069",
        "averageSessionDuration": "105.44360751612903",
        "bounceRate": "0.064516129032258063"
    },
    {
        "pagePath": "/trilhas/python/page-6/",
        "year": "2025",
        "month": "04",
        "activeUsers": "29",
        "screenPageViews": "61",
        "screenPageViewsPerSession": "0.9838709677419355",
        "screenPageViewPerUser": "2.103448275862069",
        "averageSessionDuration": "206.63901890322578",
        "bounceRate": "0.41935483870967744"
    },
    {
        "pagePath": "/trilhas/python/page-7/",
        "year": "2025",
        "month": "04",
        "activeUsers": "28",
        "screenPageViews": "32",
        "screenPageViewsPerSession": "1.0666666666666667",
        "screenPageViewPerUser": "1.1428571428571428",
        "averageSessionDuration": "31.624985766666665",
        "bounceRate": "0"
    },
    {
        "pagePath": "/blog/2024/03/13/chown-o-que-\u00e9/",
        "year": "2025",
        "month": "04",
        "activeUsers": "26",
        "screenPageViews": "28",
        "screenPageViewsPerSession": "0.90322580645161288",
        "screenPageViewPerUser": "1.0769230769230769",
        "averageSessionDuration": "95.8526274516129",
        "bounceRate": "0.38709677419354838"
    },
    {
        "pagePath": "/trilhas/python/page-13/",
        "year": "2025",
        "month": "04",
        "activeUsers": "25",
        "screenPageViews": "31",
        "screenPageViewsPerSession": "1.0333333333333334",
        "screenPageViewPerUser": "1.24",
        "averageSessionDuration": "49.388015133333326",
        "bounceRate": "0.13333333333333333"
    },
    {
        "pagePath": "/trilhas/github/page-4/",
        "year": "2025",
        "month": "04",
        "activeUsers": "23",
        "screenPageViews": "26",
        "screenPageViewsPerSession": "1.1304347826086956",
        "screenPageViewPerUser": "1.1304347826086956",
        "averageSessionDuration": "94.217071652173914",
        "bounceRate": "0"
    },
    {
        "pagePath": "/blog/",
        "year": "2025",
        "month": "04",
        "activeUsers": "22",
        "screenPageViews": "47",
        "screenPageViewsPerSession": "1.7407407407407407",
        "screenPageViewPerUser": "2.1363636363636362",
        "averageSessionDuration": "39.35283722222222",
        "bounceRate": "0.07407407407407407"
    },
    {
        "pagePath": "/trilhas/python/page-14/",
        "year": "2025",
        "month": "04",
        "activeUsers": "22",
        "screenPageViews": "24",
        "screenPageViewsPerSession": "1.0434782608695652",
        "screenPageViewPerUser": "1.0909090909090908",
        "averageSessionDuration": "56.965111565217391",
        "bounceRate": "0"
    },
    {
        "pagePath": "/blog/2024/08/07/o-que-\u00e9-endere\u00e7amento-de-mem\u00f3ria/",
        "year": "2025",
        "month": "04",
        "activeUsers": "18",
        "screenPageViews": "23",
        "screenPageViewsPerSession": "1.0454545454545454",
        "screenPageViewPerUser": "1.2777777777777777",
        "averageSessionDuration": "289.35556727272728",
        "bounceRate": "0.22727272727272727"
    },
    {
        "pagePath": "/trilhas/python/page-16/",
        "year": "2025",
        "month": "04",
        "activeUsers": "18",
        "screenPageViews": "21",
        "screenPageViewsPerSession": "1.1666666666666667",
        "screenPageViewPerUser": "1.1666666666666667",
        "averageSessionDuration": "8.8081101666666672",
        "bounceRate": "0"
    },
    {
        "pagePath": "/trilhas/python/page-11/",
        "year": "2025",
        "month": "04",
        "activeUsers": "17",
        "screenPageViews": "23",
        "screenPageViewsPerSession": "1.2777777777777777",
        "screenPageViewPerUser": "1.3529411764705883",
        "averageSessionDuration": "18.395942722222223",
        "bounceRate": "0.055555555555555552"
    },
    {
        "pagePath": "/trilhas/python/page-12/",
        "year": "2025",
        "month": "04",
        "activeUsers": "17",
        "screenPageViews": "20",
        "screenPageViewsPerSession": "1.1764705882352942",
        "screenPageViewPerUser": "1.1764705882352942",
        "averageSessionDuration": "59.622603352941177",
        "bounceRate": "0"
    },
    {
        "pagePath": "/contact/",
        "year": "2025",
        "month": "04",
        "activeUsers": "16",
        "screenPageViews": "21",
        "screenPageViewsPerSession": "1.2352941176470589",
        "screenPageViewPerUser": "1.3125",
        "averageSessionDuration": "20.084040470588235",
        "bounceRate": "0"
    },
    {
        "pagePath": "/trilhas/github/page-6/",
        "year": "2025",
        "month": "04",
        "activeUsers": "15",
        "screenPageViews": "19",
        "screenPageViewsPerSession": "1.2666666666666666",
        "screenPageViewPerUser": "1.2666666666666666",
        "averageSessionDuration": "4.2374310666666668",
        "bounceRate": "0"
    },
    {
        "pagePath": "/trilhas/github/page-7/",
        "year": "2025",
        "month": "04",
        "activeUsers": "12",
        "screenPageViews": "13",
        "screenPageViewsPerSession": "1.0833333333333333",
        "screenPageViewPerUser": "1.0833333333333333",
        "averageSessionDuration": "3.4067604166666672",
        "bounceRate": "0"
    },
    {
        "pagePath": "/trilhas/github/page-8/",
        "year": "2025",
        "month": "04",
        "activeUsers": "11",
        "screenPageViews": "11",
        "screenPageViewsPerSession": "1",
        "screenPageViewPerUser": "1",
        "averageSessionDuration": "22.491007363636363",
        "bounceRate": "0"
    },
    {
        "pagePath": "/bio/",
        "year": "2025",
        "month": "04",
        "activeUsers": "8",
        "screenPageViews": "12",
        "screenPageViewsPerSession": "1.0909090909090908",
        "screenPageViewPerUser": "1.5",
        "averageSessionDuration": "144.53645863636365",
        "bounceRate": "0.27272727272727271"
    },
    {
        "pagePath": "/blog/2022/10/14/hello-world/",
        "year": "2025",
        "month": "04",
        "activeUsers": "8",
        "screenPageViews": "9",
        "screenPageViewsPerSession": "1.125",
        "screenPageViewPerUser": "1.125",
        "averageSessionDuration": "125.53389912500002",
        "bounceRate": "0"
    },
    {
        "pagePath": "/blog/2022/11/18/codaqui-no-benfeitoriacom/",
        "year": "2025",
        "month": "04",
        "activeUsers": "5",
        "screenPageViews": "5",
        "screenPageViewsPerSession": "1",
        "screenPageViewPerUser": "1",
        "averageSessionDuration": "11.0831464",
        "bounceRate": "0"
    },
    {
        "pagePath": "/blog/2023/03/11/sucesso-na-inova\u00e7\u00e3o-do-devpr-2023/",
        "year": "2025",
        "month": "04",
        "activeUsers": "5",
        "screenPageViews": "6",
        "screenPageViewsPerSession": "1.2",
        "screenPageViewPerUser": "1.2",
        "averageSessionDuration": "12.720343600000001",
        "bounceRate": "0"
    },
    {
        "pagePath": "/ong/",
        "year": "2025",
        "month": "04",
        "activeUsers": "5",
        "screenPageViews": "6",
        "screenPageViewsPerSession": "1.2",
        "screenPageViewPerUser": "1.2",
        "averageSessionDuration": "359.2792442",
        "bounceRate": "0"
    },
    {
        "pagePath": "/quero/apoiar/",
        "year": "2025",
        "month": "04",
        "activeUsers": "5",
        "screenPageViews": "11",
        "screenPageViewsPerSession": "1",
        "screenPageViewPerUser": "2.2",
        "averageSessionDuration": "70.00278818181819",
        "bounceRate": "0.54545454545454541"
    },
    {
        "pagePath": "/timeline/",
        "year": "2025",
        "month": "04",
        "activeUsers": "4",
        "screenPageViews": "5",
        "screenPageViewsPerSession": "1.25",
        "screenPageViewPerUser": "1.25",
        "averageSessionDuration": "9.739953",
        "bounceRate": "0"
    },
    {
        "pagePath": "/blog/archive/2024/",
        "year": "2025",
        "month": "04",
        "activeUsers": "3",
        "screenPageViews": "3",
        "screenPageViewsPerSession": "1",
        "screenPageViewPerUser": "1",
        "averageSessionDuration": "592.00031433333334",
        "bounceRate": "0.33333333333333331"
    },
    {
        "pagePath": "/trilhas/python/bonus-roadmap/",
        "year": "2025",
        "month": "04",
        "activeUsers": "3",
        "screenPageViews": "4",
        "screenPageViewsPerSession": "1.3333333333333333",
        "screenPageViewPerUser": "1.3333333333333333",
        "averageSessionDuration": "107.50228933333334",
        "bounceRate": "0"
    },
    {
        "pagePath": "/blog/2024/07/22/devparan\u00e1-e-codaqui-unidos-pela-comunidade/",
        "year": "2025",
        "month": "04",
        "activeUsers": "2",
        "screenPageViews": "2",
        "screenPageViewsPerSession": "1",
        "screenPageViewPerUser": "1",
        "averageSessionDuration": "3.0147725000000003",
        "bounceRate": "0"
    },
    {
        "pagePath": "/codaqui/institucional/gh-pages-develop/blog/2025/04/02/o-papel-de-uma-sre-em-sistemas-financeiros-cr\u00edticos/index.html",
        "year": "2025",
        "month": "04",
        "activeUsers": "2",
        "screenPageViews": "3",
        "screenPageViewsPerSession": "1",
        "screenPageViewPerUser": "1.5",
        "averageSessionDuration": "41.485051666666671",
        "bounceRate": "0.66666666666666663"
    },
    {
        "pagePath": "/blog/2023/10/23/codaqui-apoia-campeonato-de-skate-em-marialva/",
        "year": "2025",
        "month": "04",
        "activeUsers": "1",
        "screenPageViews": "1",
        "screenPageViewsPerSession": "1",
        "screenPageViewPerUser": "1",
        "averageSessionDuration": "33.413587",
        "bounceRate": "0"
    },
    {
        "pagePath": "/blog/2024/09/17/presta\u00e7\u00e3o-de-contas-do-devpr-conf-2024/",
        "year": "2025",
        "month": "04",
        "activeUsers": "1",
        "screenPageViews": "1",
        "screenPageViewsPerSession": "1",
        "screenPageViewPerUser": "1",
        "averageSessionDuration": "1.993002",
        "bounceRate": "0"
    },
    {
        "pagePath": "/blog/2025/04/02/o-papel-de-uma-sre-em-sistemas-financeiros-cr\u00edticos/",
        "year": "2025",
        "month": "04",
        "activeUsers": "1",
        "screenPageViews": "37",
        "screenPageViewsPerSession": "1.4230769230769231",
        "screenPageViewPerUser": "37",
        "averageSessionDuration": "350.36851211538459",
        "bounceRate": "0.76923076923076927"
    },
    {
        "pagePath": "/blog/archive/2025/",
        "year": "2025",
        "month": "04",
        "activeUsers": "1",
        "screenPageViews": "4",
        "screenPageViewsPerSession": "4",
        "screenPageViewPerUser": "4",
        "averageSessionDuration": "301.94633",
        "bounceRate": "1"
    },
    {
        "pagePath": "/blog/category/curiosidade/",
        "year": "2025",
        "month": "04",
        "activeUsers": "1",
        "screenPageViews": "2",
        "screenPageViewsPerSession": "2",
        "screenPageViewPerUser": "2",
        "averageSessionDuration": "3.29601",
        "bounceRate": "1"
    },
    {
        "pagePath": "/blog/category/institucional/",
        "year": "2025",
        "month": "04",
        "activeUsers": "1",
        "screenPageViews": "3",
        "screenPageViewsPerSession": "3",
        "screenPageViewPerUser": "3",
        "averageSessionDuration": "278.213398",
        "bounceRate": "1"
    },
    {
        "pagePath": "/blog/category/projetos/",
        "year": "2025",
        "month": "04",
        "activeUsers": "1",
        "screenPageViews": "2",
        "screenPageViewsPerSession": "2",
        "screenPageViewPerUser": "2",
        "averageSessionDuration": "1.495841",
        "bounceRate": "1"
    },
    {
        "pagePath": "/blog/category/tutoriais/",
        "year": "2025",
        "month": "04",
        "activeUsers": "1",
        "screenPageViews": "1",
        "screenPageViewsPerSession": "1",
        "screenPageViewPerUser": "1",
        "averageSessionDuration": "1.785915",
        "bounceRate": "1"
    },
    {
        "pagePath": "/codaqui/institucional/gh-pages-develop/blog/index.html",
        "year": "2025",
        "month": "04",
        "activeUsers": "1",
        "screenPageViews": "1",
        "screenPageViewsPerSession": "1",
        "screenPageViewPerUser": "1",
        "averageSessionDuration": "5.324067",
        "bounceRate": "0"
    },
    {
        "pagePath": "/codaqui/institucional/gh-pages-develop/index.html",
        "year": "2025",
        "month": "04",
        "activeUsers": "1",
        "screenPageViews": "1",
        "screenPageViewsPerSession": "1",
        "screenPageViewPerUser": "1",
        "averageSessionDuration": "3.415399",
        "bounceRate": "0"
    },
    {
        "pagePath": "/conduta/",
        "year": "2025",
        "month": "04",
        "activeUsers": "1",
        "screenPageViews": "2",
        "screenPageViewsPerSession": "2",
        "screenPageViewPerUser": "2",
        "averageSessionDuration": "26.260118",
        "bounceRate": "0"
    },
    {
        "pagePath": "/pais_responsaveis/",
        "year": "2025",
        "month": "04",
        "activeUsers": "1",
        "screenPageViews": "2",
        "screenPageViewsPerSession": "2",
        "screenPageViewPerUser": "2",
        "averageSessionDuration": "3.520477",
        "bounceRate": "0"
    },
    {
        "pagePath": "/trilhas/java",
        "year": "2025",
        "month": "04",
        "activeUsers": "1",
        "screenPageViews": "1",
        "screenPageViewsPerSession": "1",
        "screenPageViewPerUser": "1",
        "averageSessionDuration": "6.828951",
        "bounceRate": "0"
    },
    {
        "pagePath": "/trilhas/javascript/",
        "year": "2025",
        "month": "04",
        "activeUsers": "1",
        "screenPageViews": "1",
        "screenPageViewsPerSession": "1",
        "screenPageViewPerUser": "1",
        "averageSessionDuration": "3.163477",
        "bounceRate": "0"
    }
]