[
    {
        "pagePath": "/blog/2026/03/30/curso-introducao-python",
        "year": "2026",
        "month": "04",
        "activeUsers": "486",
        "screenPageViews": "593",
        "screenPageViewsPerSession": "1.1316793893129771",
        "screenPageViewPerUser": "1.2201646090534979",
        "averageSessionDuration": "81.583840730916052",
        "bounceRate": "0.44656488549618323"
    },
    {
        "pagePath": "/trilhas/python/",
        "year": "2026",
        "month": "04",
        "activeUsers": "219",
        "screenPageViews": "333",
        "screenPageViewsPerSession": "1.1174496644295302",
        "screenPageViewPerUser": "1.5205479452054795",
        "averageSessionDuration": "43.56277496979866",
        "bounceRate": "0.60738255033557043"
    },
    {
        "pagePath": "/trilhas/python",
        "year": "2026",
        "month": "04",
        "activeUsers": "130",
        "screenPageViews": "388",
        "screenPageViewsPerSession": "1.9019607843137254",
        "screenPageViewPerUser": "2.9846153846153847",
        "averageSessionDuration": "67.53992949509805",
        "bounceRate": "0.15686274509803921"
    },
    {
        "pagePath": "/participe/estudar",
        "year": "2026",
        "month": "04",
        "activeUsers": "117",
        "screenPageViews": "261",
        "screenPageViewsPerSession": "1.9051094890510949",
        "screenPageViewPerUser": "2.2307692307692308",
        "averageSessionDuration": "80.647039496350374",
        "bounceRate": "0.087591240875912413"
    },
    {
        "pagePath": "/trilhas/python/page-1",
        "year": "2026",
        "month": "04",
        "activeUsers": "115",
        "screenPageViews": "408",
        "screenPageViewsPerSession": "2",
        "screenPageViewPerUser": "3.5478260869565217",
        "averageSessionDuration": "259.69388379901966",
        "bounceRate": "0.27941176470588236"
    },
    {
        "pagePath": "/trilhas/python/page-1/",
        "year": "2026",
        "month": "04",
        "activeUsers": "106",
        "screenPageViews": "206",
        "screenPageViewsPerSession": "1.0404040404040404",
        "screenPageViewPerUser": "1.9433962264150944",
        "averageSessionDuration": "106.19141673232322",
        "bounceRate": "0.64646464646464652"
    },
    {
        "pagePath": "/trilhas/python/page-2",
        "year": "2026",
        "month": "04",
        "activeUsers": "83",
        "screenPageViews": "333",
        "screenPageViewsPerSession": "2.5813953488372094",
        "screenPageViewPerUser": "4.0120481927710845",
        "averageSessionDuration": "199.40706422480619",
        "bounceRate": "0.18604651162790697"
    },
    {
        "pagePath": "/blog/2026/03/30/curso-educacao-financeira",
        "year": "2026",
        "month": "04",
        "activeUsers": "74",
        "screenPageViews": "127",
        "screenPageViewsPerSession": "1.1981132075471699",
        "screenPageViewPerUser": "1.7162162162162162",
        "averageSessionDuration": "91.112302320754708",
        "bounceRate": "0.40566037735849059"
    },
    {
        "pagePath": "/trilhas/python/page-3",
        "year": "2026",
        "month": "04",
        "activeUsers": "71",
        "screenPageViews": "346",
        "screenPageViewsPerSession": "2.1625",
        "screenPageViewPerUser": "4.873239436619718",
        "averageSessionDuration": "209.94121643125004",
        "bounceRate": "0.25625"
    },
    {
        "pagePath": "/eventos",
        "year": "2026",
        "month": "04",
        "activeUsers": "69",
        "screenPageViews": "182",
        "screenPageViewsPerSession": "1.5826086956521739",
        "screenPageViewPerUser": "2.63768115942029",
        "averageSessionDuration": "158.44014456521742",
        "bounceRate": "0.34782608695652173"
    },
    {
        "pagePath": "/participe/apoiar",
        "year": "2026",
        "month": "04",
        "activeUsers": "53",
        "screenPageViews": "224",
        "screenPageViewsPerSession": "2.2857142857142856",
        "screenPageViewPerUser": "4.2264150943396226",
        "averageSessionDuration": "214.75124696938775",
        "bounceRate": "0.23469387755102042"
    },
    {
        "pagePath": "/trilhas/python/page-3/",
        "year": "2026",
        "month": "04",
        "activeUsers": "53",
        "screenPageViews": "73",
        "screenPageViewsPerSession": "0.87951807228915657",
        "screenPageViewPerUser": "1.3773584905660377",
        "averageSessionDuration": "87.910920674698787",
        "bounceRate": "0.68674698795180722"
    },
    {
        "pagePath": "/trilhas/python/page-5",
        "year": "2026",
        "month": "04",
        "activeUsers": "46",
        "screenPageViews": "165",
        "screenPageViewsPerSession": "2.323943661971831",
        "screenPageViewPerUser": "3.5869565217391304",
        "averageSessionDuration": "153.57543381690144",
        "bounceRate": "0.11267605633802817"
    },
    {
        "pagePath": "/trilhas/python/page-4",
        "year": "2026",
        "month": "04",
        "activeUsers": "44",
        "screenPageViews": "142",
        "screenPageViewsPerSession": "2.0285714285714285",
        "screenPageViewPerUser": "3.2272727272727271",
        "averageSessionDuration": "197.14574394285717",
        "bounceRate": "0.18571428571428572"
    },
    {
        "pagePath": "/projetos",
        "year": "2026",
        "month": "04",
        "activeUsers": "40",
        "screenPageViews": "100",
        "screenPageViewsPerSession": "1.9607843137254901",
        "screenPageViewPerUser": "2.5",
        "averageSessionDuration": "112.55885815686274",
        "bounceRate": "0.19607843137254902"
    },
    {
        "pagePath": "/auth/callback",
        "year": "2026",
        "month": "04",
        "activeUsers": "31",
        "screenPageViews": "44",
        "screenPageViewsPerSession": "1.0476190476190477",
        "screenPageViewPerUser": "1.4193548387096775",
        "averageSessionDuration": "28.623318928571432",
        "bounceRate": "0"
    },
    {
        "pagePath": "/transparencia",
        "year": "2026",
        "month": "04",
        "activeUsers": "29",
        "screenPageViews": "238",
        "screenPageViewsPerSession": "2.5869565217391304",
        "screenPageViewPerUser": "8.2068965517241388",
        "averageSessionDuration": "179.54028525",
        "bounceRate": "0.13043478260869565"
    },
    {
        "pagePath": "/bio",
        "year": "2026",
        "month": "04",
        "activeUsers": "25",
        "screenPageViews": "41",
        "screenPageViewsPerSession": "1.4642857142857142",
        "screenPageViewPerUser": "1.64",
        "averageSessionDuration": "90.078957714285721",
        "bounceRate": "0.17857142857142858"
    },
    {
        "pagePath": "/trilhas",
        "year": "2026",
        "month": "04",
        "activeUsers": "25",
        "screenPageViews": "58",
        "screenPageViewsPerSession": "2.0714285714285716",
        "screenPageViewPerUser": "2.32",
        "averageSessionDuration": "46.635600964285722",
        "bounceRate": "0.17857142857142858"
    },
    {
        "pagePath": "/blog",
        "year": "2026",
        "month": "04",
        "activeUsers": "24",
        "screenPageViews": "114",
        "screenPageViewsPerSession": "2.85",
        "screenPageViewPerUser": "4.75",
        "averageSessionDuration": "70.702028650000017",
        "bounceRate": "0.15"
    },
    {
        "pagePath": "/sobre/equipe",
        "year": "2026",
        "month": "04",
        "activeUsers": "23",
        "screenPageViews": "51",
        "screenPageViewsPerSession": "1.8214285714285714",
        "screenPageViewPerUser": "2.2173913043478262",
        "averageSessionDuration": "93.001890928571427",
        "bounceRate": "0.21428571428571427"
    },
    {
        "pagePath": "/trilhas/python/page-6",
        "year": "2026",
        "month": "04",
        "activeUsers": "23",
        "screenPageViews": "61",
        "screenPageViewsPerSession": "2.1785714285714284",
        "screenPageViewPerUser": "2.652173913043478",
        "averageSessionDuration": "36.280551571428575",
        "bounceRate": "0.035714285714285712"
    },
    {
        "pagePath": "/trilhas/python/page-8",
        "year": "2026",
        "month": "04",
        "activeUsers": "22",
        "screenPageViews": "67",
        "screenPageViewsPerSession": "1.8611111111111112",
        "screenPageViewPerUser": "3.0454545454545454",
        "averageSessionDuration": "21.181236166666668",
        "bounceRate": "0.25"
    },
    {
        "pagePath": "/contato",
        "year": "2026",
        "month": "04",
        "activeUsers": "21",
        "screenPageViews": "35",
        "screenPageViewsPerSession": "1.5909090909090908",
        "screenPageViewPerUser": "1.6666666666666667",
        "averageSessionDuration": "70.644861181818186",
        "bounceRate": "0.18181818181818182"
    },
    {
        "pagePath": "/participe/mentoria",
        "year": "2026",
        "month": "04",
        "activeUsers": "21",
        "screenPageViews": "43",
        "screenPageViewsPerSession": "1.72",
        "screenPageViewPerUser": "2.0476190476190474",
        "averageSessionDuration": "115.72303991999998",
        "bounceRate": "0.12"
    },
    {
        "pagePath": "/quero/estudar",
        "year": "2026",
        "month": "04",
        "activeUsers": "21",
        "screenPageViews": "26",
        "screenPageViewsPerSession": "1.0833333333333333",
        "screenPageViewPerUser": "1.2380952380952381",
        "averageSessionDuration": "28.206518791666671",
        "bounceRate": "0.041666666666666664"
    },
    {
        "pagePath": "/sobre/ong",
        "year": "2026",
        "month": "04",
        "activeUsers": "20",
        "screenPageViews": "109",
        "screenPageViewsPerSession": "2.4222222222222221",
        "screenPageViewPerUser": "5.45",
        "averageSessionDuration": "94.956927288888878",
        "bounceRate": "0.1111111111111111"
    },
    {
        "pagePath": "/trilhas/python/page-7",
        "year": "2026",
        "month": "04",
        "activeUsers": "20",
        "screenPageViews": "60",
        "screenPageViewsPerSession": "2.7272727272727271",
        "screenPageViewPerUser": "3",
        "averageSessionDuration": "42.754494636363638",
        "bounceRate": "0.090909090909090912"
    },
    {
        "pagePath": "/trilhas/github",
        "year": "2026",
        "month": "04",
        "activeUsers": "17",
        "screenPageViews": "41",
        "screenPageViewsPerSession": "2.2777777777777777",
        "screenPageViewPerUser": "2.4117647058823528",
        "averageSessionDuration": "24.466660888888889",
        "bounceRate": "0.1111111111111111"
    },
    {
        "pagePath": "/trilhas/python/page-9",
        "year": "2026",
        "month": "04",
        "activeUsers": "17",
        "screenPageViews": "40",
        "screenPageViewsPerSession": "2.1052631578947367",
        "screenPageViewPerUser": "2.3529411764705883",
        "averageSessionDuration": "98.505738684210527",
        "bounceRate": "0.052631578947368418"
    },
    {
        "pagePath": "/membro",
        "year": "2026",
        "month": "04",
        "activeUsers": "16",
        "screenPageViews": "56",
        "screenPageViewsPerSession": "1.1428571428571428",
        "screenPageViewPerUser": "3.5",
        "averageSessionDuration": "173.30784918367343",
        "bounceRate": "0.12244897959183673"
    },
    {
        "pagePath": "/trilhas/python/page-13/",
        "year": "2026",
        "month": "04",
        "activeUsers": "16",
        "screenPageViews": "21",
        "screenPageViewsPerSession": "1.05",
        "screenPageViewPerUser": "1.3125",
        "averageSessionDuration": "248.09719775",
        "bounceRate": "0.5"
    },
    {
        "pagePath": "/membros",
        "year": "2026",
        "month": "04",
        "activeUsers": "14",
        "screenPageViews": "50",
        "screenPageViewsPerSession": "2.1739130434782608",
        "screenPageViewPerUser": "3.5714285714285716",
        "averageSessionDuration": "57.86124460869565",
        "bounceRate": "0.13043478260869565"
    },
    {
        "pagePath": "/trilhas/python/page-10",
        "year": "2026",
        "month": "04",
        "activeUsers": "14",
        "screenPageViews": "30",
        "screenPageViewsPerSession": "2",
        "screenPageViewPerUser": "2.1428571428571428",
        "averageSessionDuration": "182.00545393333334",
        "bounceRate": "0.13333333333333333"
    },
    {
        "pagePath": "/trilhas/python/page-13",
        "year": "2026",
        "month": "04",
        "activeUsers": "14",
        "screenPageViews": "24",
        "screenPageViewsPerSession": "1.7142857142857142",
        "screenPageViewPerUser": "1.7142857142857142",
        "averageSessionDuration": "48.473277857142854",
        "bounceRate": "0.21428571428571427"
    },
    {
        "pagePath": "/trilhas/python/page-16",
        "year": "2026",
        "month": "04",
        "activeUsers": "14",
        "screenPageViews": "28",
        "screenPageViewsPerSession": "1.8666666666666667",
        "screenPageViewPerUser": "2",
        "averageSessionDuration": "64.946191800000008",
        "bounceRate": "0.13333333333333333"
    },
    {
        "pagePath": "/trilhas/",
        "year": "2026",
        "month": "04",
        "activeUsers": "13",
        "screenPageViews": "17",
        "screenPageViewsPerSession": "1",
        "screenPageViewPerUser": "1.3076923076923077",
        "averageSessionDuration": "115.94548529411766",
        "bounceRate": "0.47058823529411764"
    },
    {
        "pagePath": "/trilhas/github/page-1",
        "year": "2026",
        "month": "04",
        "activeUsers": "13",
        "screenPageViews": "26",
        "screenPageViewsPerSession": "1.625",
        "screenPageViewPerUser": "2",
        "averageSessionDuration": "17.775340375000003",
        "bounceRate": "0.0625"
    },
    {
        "pagePath": "/trilhas/python/page-11",
        "year": "2026",
        "month": "04",
        "activeUsers": "13",
        "screenPageViews": "30",
        "screenPageViewsPerSession": "2.3076923076923075",
        "screenPageViewPerUser": "2.3076923076923075",
        "averageSessionDuration": "79.072790230769229",
        "bounceRate": "0.076923076923076927"
    },
    {
        "pagePath": "/trilhas/python/page-14",
        "year": "2026",
        "month": "04",
        "activeUsers": "12",
        "screenPageViews": "21",
        "screenPageViewsPerSession": "1.6153846153846154",
        "screenPageViewPerUser": "1.75",
        "averageSessionDuration": "100.54475507692307",
        "bounceRate": "0.30769230769230771"
    },
    {
        "pagePath": "/trilhas/python/page-15",
        "year": "2026",
        "month": "04",
        "activeUsers": "12",
        "screenPageViews": "20",
        "screenPageViewsPerSession": "1.6666666666666667",
        "screenPageViewPerUser": "1.6666666666666667",
        "averageSessionDuration": "152.28748675",
        "bounceRate": "0.25"
    },
    {
        "pagePath": "/trilhas/python/page-4/",
        "year": "2026",
        "month": "04",
        "activeUsers": "12",
        "screenPageViews": "36",
        "screenPageViewsPerSession": "1.2",
        "screenPageViewPerUser": "3",
        "averageSessionDuration": "50.55355196666666",
        "bounceRate": "0.6333333333333333"
    },
    {
        "pagePath": "/membros/perfil",
        "year": "2026",
        "month": "04",
        "activeUsers": "11",
        "screenPageViews": "23",
        "screenPageViewsPerSession": "1.3529411764705883",
        "screenPageViewPerUser": "2.0909090909090908",
        "averageSessionDuration": "89.263925117647062",
        "bounceRate": "0.058823529411764705"
    },
    {
        "pagePath": "/sobre/insights",
        "year": "2026",
        "month": "04",
        "activeUsers": "11",
        "screenPageViews": "61",
        "screenPageViewsPerSession": "3.2105263157894739",
        "screenPageViewPerUser": "5.5454545454545459",
        "averageSessionDuration": "202.99480878947369",
        "bounceRate": "0.15789473684210525"
    },
    {
        "pagePath": "/trilhas/python/page-12",
        "year": "2026",
        "month": "04",
        "activeUsers": "11",
        "screenPageViews": "22",
        "screenPageViewsPerSession": "2",
        "screenPageViewPerUser": "2",
        "averageSessionDuration": "39.267522363636367",
        "bounceRate": "0.090909090909090912"
    },
    {
        "pagePath": "/trilhas/python/page-14/",
        "year": "2026",
        "month": "04",
        "activeUsers": "9",
        "screenPageViews": "15",
        "screenPageViewsPerSession": "1.0714285714285714",
        "screenPageViewPerUser": "1.6666666666666667",
        "averageSessionDuration": "250.1258785",
        "bounceRate": "0.5"
    },
    {
        "pagePath": "/sobre/pais-responsaveis",
        "year": "2026",
        "month": "04",
        "activeUsers": "8",
        "screenPageViews": "12",
        "screenPageViewsPerSession": "1.5",
        "screenPageViewPerUser": "1.5",
        "averageSessionDuration": "11.514161",
        "bounceRate": "0.5"
    },
    {
        "pagePath": "/trilhas/github/page-2",
        "year": "2026",
        "month": "04",
        "activeUsers": "8",
        "screenPageViews": "17",
        "screenPageViewsPerSession": "1.7",
        "screenPageViewPerUser": "2.125",
        "averageSessionDuration": "28.791914499999997",
        "bounceRate": "0.2"
    },
    {
        "pagePath": "/admin/reembolsos",
        "year": "2026",
        "month": "04",
        "activeUsers": "6",
        "screenPageViews": "31",
        "screenPageViewsPerSession": "1.3478260869565217",
        "screenPageViewPerUser": "5.166666666666667",
        "averageSessionDuration": "162.17556747826083",
        "bounceRate": "0.043478260869565216"
    },
    {
        "pagePath": "/trilhas/github/page-3",
        "year": "2026",
        "month": "04",
        "activeUsers": "6",
        "screenPageViews": "12",
        "screenPageViewsPerSession": "2",
        "screenPageViewPerUser": "2",
        "averageSessionDuration": "114.13548616666667",
        "bounceRate": "0.16666666666666666"
    },
    {
        "pagePath": "/trilhas/github/page-4",
        "year": "2026",
        "month": "04",
        "activeUsers": "6",
        "screenPageViews": "13",
        "screenPageViewsPerSession": "2.1666666666666665",
        "screenPageViewPerUser": "2.1666666666666665",
        "averageSessionDuration": "19.014871833333334",
        "bounceRate": "0.16666666666666666"
    },
    {
        "pagePath": "/trilhas/github/page-5",
        "year": "2026",
        "month": "04",
        "activeUsers": "6",
        "screenPageViews": "11",
        "screenPageViewsPerSession": "1.8333333333333333",
        "screenPageViewPerUser": "1.8333333333333333",
        "averageSessionDuration": "17.323780333333335",
        "bounceRate": "0.16666666666666666"
    },
    {
        "pagePath": "/admin",
        "year": "2026",
        "month": "04",
        "activeUsers": "5",
        "screenPageViews": "35",
        "screenPageViewsPerSession": "1.5909090909090908",
        "screenPageViewPerUser": "7",
        "averageSessionDuration": "42.489485863636361",
        "bounceRate": "0.045454545454545456"
    },
    {
        "pagePath": "/blog/category/curso",
        "year": "2026",
        "month": "04",
        "activeUsers": "5",
        "screenPageViews": "10",
        "screenPageViewsPerSession": "1.6666666666666667",
        "screenPageViewPerUser": "2",
        "averageSessionDuration": "6.0936355",
        "bounceRate": "0.16666666666666666"
    },
    {
        "pagePath": "/sobre/conduta",
        "year": "2026",
        "month": "04",
        "activeUsers": "5",
        "screenPageViews": "8",
        "screenPageViewsPerSession": "1.6",
        "screenPageViewPerUser": "1.6",
        "averageSessionDuration": "124.2848316",
        "bounceRate": "0.4"
    },
    {
        "pagePath": "/trilhas/github/page-6",
        "year": "2026",
        "month": "04",
        "activeUsers": "5",
        "screenPageViews": "9",
        "screenPageViewsPerSession": "1.8",
        "screenPageViewPerUser": "1.8",
        "averageSessionDuration": "63.148285800000011",
        "bounceRate": "0.2"
    },
    {
        "pagePath": "/trilhas/python/page-2/",
        "year": "2026",
        "month": "04",
        "activeUsers": "5",
        "screenPageViews": "25",
        "screenPageViewsPerSession": "1",
        "screenPageViewPerUser": "5",
        "averageSessionDuration": "13.991920039999998",
        "bounceRate": "0.84"
    },
    {
        "pagePath": "/blog/2023/02/14/devpr-starter---codaqui/",
        "year": "2026",
        "month": "04",
        "activeUsers": "4",
        "screenPageViews": "4",
        "screenPageViewsPerSession": "1",
        "screenPageViewPerUser": "1",
        "averageSessionDuration": "2.42607425",
        "bounceRate": "1"
    },
    {
        "pagePath": "/blog/category/programacao",
        "year": "2026",
        "month": "04",
        "activeUsers": "4",
        "screenPageViews": "7",
        "screenPageViewsPerSession": "1.75",
        "screenPageViewPerUser": "1.75",
        "averageSessionDuration": "36.8837815",
        "bounceRate": "0"
    },
    {
        "pagePath": "/trilhas/github/page-7",
        "year": "2026",
        "month": "04",
        "activeUsers": "4",
        "screenPageViews": "8",
        "screenPageViewsPerSession": "1.6",
        "screenPageViewPerUser": "2",
        "averageSessionDuration": "1.9783974",
        "bounceRate": "0.4"
    },
    {
        "pagePath": "/trilhas/github/page-8",
        "year": "2026",
        "month": "04",
        "activeUsers": "4",
        "screenPageViews": "7",
        "screenPageViewsPerSession": "1.75",
        "screenPageViewPerUser": "1.75",
        "averageSessionDuration": "1.7625745",
        "bounceRate": "0.25"
    },
    {
        "pagePath": "/@endersonmenezes",
        "year": "2026",
        "month": "04",
        "activeUsers": "3",
        "screenPageViews": "7",
        "screenPageViewsPerSession": "1.4",
        "screenPageViewPerUser": "2.3333333333333335",
        "averageSessionDuration": "4.5135904",
        "bounceRate": "0"
    },
    {
        "pagePath": "/blog/2026/03/30/curso-educacao-financeira/",
        "year": "2026",
        "month": "04",
        "activeUsers": "3",
        "screenPageViews": "5",
        "screenPageViewsPerSession": "1.25",
        "screenPageViewPerUser": "1.6666666666666667",
        "averageSessionDuration": "27.3239645",
        "bounceRate": "0.5"
    },
    {
        "pagePath": "/blog/category/tutoriais",
        "year": "2026",
        "month": "04",
        "activeUsers": "3",
        "screenPageViews": "5",
        "screenPageViewsPerSession": "1.6666666666666667",
        "screenPageViewPerUser": "1.6666666666666667",
        "averageSessionDuration": "9.0134983333333327",
        "bounceRate": "0"
    },
    {
        "pagePath": "/projetos/",
        "year": "2026",
        "month": "04",
        "activeUsers": "3",
        "screenPageViews": "3",
        "screenPageViewsPerSession": "0.75",
        "screenPageViewPerUser": "1",
        "averageSessionDuration": "12.7684715",
        "bounceRate": "0.25"
    },
    {
        "pagePath": "/quero/apoiar/",
        "year": "2026",
        "month": "04",
        "activeUsers": "3",
        "screenPageViews": "3",
        "screenPageViewsPerSession": "1",
        "screenPageViewPerUser": "1",
        "averageSessionDuration": "19.758663333333335",
        "bounceRate": "0"
    },
    {
        "pagePath": "/trilhas/python/page-5/",
        "year": "2026",
        "month": "04",
        "activeUsers": "3",
        "screenPageViews": "6",
        "screenPageViewsPerSession": "1",
        "screenPageViewPerUser": "2",
        "averageSessionDuration": "16.857903166666667",
        "bounceRate": "0.66666666666666663"
    },
    {
        "pagePath": "/@iamdatagabs",
        "year": "2026",
        "month": "04",
        "activeUsers": "2",
        "screenPageViews": "2",
        "screenPageViewsPerSession": "1",
        "screenPageViewPerUser": "1",
        "averageSessionDuration": "0.506722",
        "bounceRate": "0"
    },
    {
        "pagePath": "/blog/2023/01/05/codaqui-na-confer\u00eancia-do-devpr-2023/",
        "year": "2026",
        "month": "04",
        "activeUsers": "2",
        "screenPageViews": "2",
        "screenPageViewsPerSession": "1",
        "screenPageViewPerUser": "1",
        "averageSessionDuration": "0.582298",
        "bounceRate": "1"
    },
    {
        "pagePath": "/blog/2025/08/22/cloudflare-tunnel-economizando-ipv4-ao-expor-servicos-em-vms",
        "year": "2026",
        "month": "04",
        "activeUsers": "2",
        "screenPageViews": "4",
        "screenPageViewsPerSession": "2",
        "screenPageViewPerUser": "2",
        "averageSessionDuration": "12.1381485",
        "bounceRate": "0"
    },
    {
        "pagePath": "/blog/2025/10/23/presta\u00e7\u00e3o-de-contas-do-devpr-conf-2025/",
        "year": "2026",
        "month": "04",
        "activeUsers": "2",
        "screenPageViews": "2",
        "screenPageViewsPerSession": "1",
        "screenPageViewPerUser": "1",
        "averageSessionDuration": "0.3006105",
        "bounceRate": "1"
    },
    {
        "pagePath": "/blog/category/institucional",
        "year": "2026",
        "month": "04",
        "activeUsers": "2",
        "screenPageViews": "3",
        "screenPageViewsPerSession": "1.5",
        "screenPageViewPerUser": "1.5",
        "averageSessionDuration": "5.5464850000000006",
        "bounceRate": "0"
    },
    {
        "pagePath": "/membro/editar",
        "year": "2026",
        "month": "04",
        "activeUsers": "2",
        "screenPageViews": "2",
        "screenPageViewsPerSession": "1",
        "screenPageViewPerUser": "1",
        "averageSessionDuration": "4.064272",
        "bounceRate": "0"
    },
    {
        "pagePath": "/quero/estudar/",
        "year": "2026",
        "month": "04",
        "activeUsers": "2",
        "screenPageViews": "2",
        "screenPageViewsPerSession": "1",
        "screenPageViewPerUser": "1",
        "averageSessionDuration": "3.9217435",
        "bounceRate": "0"
    },
    {
        "pagePath": "/quero/mentoria/",
        "year": "2026",
        "month": "04",
        "activeUsers": "2",
        "screenPageViews": "2",
        "screenPageViewsPerSession": "1",
        "screenPageViewPerUser": "1",
        "averageSessionDuration": "0.8982425",
        "bounceRate": "0"
    },
    {
        "pagePath": "/trilhas/puthon",
        "year": "2026",
        "month": "04",
        "activeUsers": "2",
        "screenPageViews": "2",
        "screenPageViewsPerSession": "1",
        "screenPageViewPerUser": "1",
        "averageSessionDuration": "16.9987",
        "bounceRate": "0"
    },
    {
        "pagePath": "/trilhas/python/page-10/",
        "year": "2026",
        "month": "04",
        "activeUsers": "2",
        "screenPageViews": "2",
        "screenPageViewsPerSession": "1",
        "screenPageViewPerUser": "1",
        "averageSessionDuration": "71.5918295",
        "bounceRate": "0.5"
    },
    {
        "pagePath": "/trilhas/python/page-11/",
        "year": "2026",
        "month": "04",
        "activeUsers": "2",
        "screenPageViews": "2",
        "screenPageViewsPerSession": "1",
        "screenPageViewPerUser": "1",
        "averageSessionDuration": "35.0500615",
        "bounceRate": "0"
    },
    {
        "pagePath": "/@ByIvo",
        "year": "2026",
        "month": "04",
        "activeUsers": "1",
        "screenPageViews": "1",
        "screenPageViewsPerSession": "1",
        "screenPageViewPerUser": "1",
        "averageSessionDuration": "0.167336",
        "bounceRate": "0"
    },
    {
        "pagePath": "/@Luasandrade",
        "year": "2026",
        "month": "04",
        "activeUsers": "1",
        "screenPageViews": "1",
        "screenPageViewsPerSession": "1",
        "screenPageViewPerUser": "1",
        "averageSessionDuration": "17.125804",
        "bounceRate": "0"
    },
    {
        "pagePath": "/@danilopinotti",
        "year": "2026",
        "month": "04",
        "activeUsers": "1",
        "screenPageViews": "1",
        "screenPageViewsPerSession": "1",
        "screenPageViewPerUser": "1",
        "averageSessionDuration": "0.605359",
        "bounceRate": "0"
    },
    {
        "pagePath": "/@fredmosc",
        "year": "2026",
        "month": "04",
        "activeUsers": "1",
        "screenPageViews": "1",
        "screenPageViewsPerSession": "1",
        "screenPageViewPerUser": "1",
        "averageSessionDuration": "0.361601",
        "bounceRate": "0"
    },
    {
        "pagePath": "/@sschonss",
        "year": "2026",
        "month": "04",
        "activeUsers": "1",
        "screenPageViews": "1",
        "screenPageViewsPerSession": "1",
        "screenPageViewPerUser": "1",
        "averageSessionDuration": "0.163595",
        "bounceRate": "0"
    },
    {
        "pagePath": "/admin/fornecedores",
        "year": "2026",
        "month": "04",
        "activeUsers": "1",
        "screenPageViews": "3",
        "screenPageViewsPerSession": "1",
        "screenPageViewPerUser": "3",
        "averageSessionDuration": "8.059059333333332",
        "bounceRate": "0"
    },
    {
        "pagePath": "/admin/pagamentos",
        "year": "2026",
        "month": "04",
        "activeUsers": "1",
        "screenPageViews": "3",
        "screenPageViewsPerSession": "1",
        "screenPageViewPerUser": "3",
        "averageSessionDuration": "93.033384333333345",
        "bounceRate": "0"
    },
    {
        "pagePath": "/admin/transferencias",
        "year": "2026",
        "month": "04",
        "activeUsers": "1",
        "screenPageViews": "2",
        "screenPageViewsPerSession": "1",
        "screenPageViewPerUser": "2",
        "averageSessionDuration": "118.866679",
        "bounceRate": "0"
    },
    {
        "pagePath": "/blog/2023/03/01/codaqui-e-seu-boletim-de-seguranca",
        "year": "2026",
        "month": "04",
        "activeUsers": "1",
        "screenPageViews": "1",
        "screenPageViewsPerSession": "1",
        "screenPageViewPerUser": "1",
        "averageSessionDuration": "0",
        "bounceRate": "1"
    },
    {
        "pagePath": "/blog/2024/03/13/chown-o-que-\u00e9/",
        "year": "2026",
        "month": "04",
        "activeUsers": "1",
        "screenPageViews": "1",
        "screenPageViewsPerSession": "1",
        "screenPageViewPerUser": "1",
        "averageSessionDuration": "2.895249",
        "bounceRate": "1"
    },
    {
        "pagePath": "/blog/2024/08/07/o-que-e-enderecamento-de-memoria",
        "year": "2026",
        "month": "04",
        "activeUsers": "1",
        "screenPageViews": "2",
        "screenPageViewsPerSession": "2",
        "screenPageViewPerUser": "2",
        "averageSessionDuration": "4.123096",
        "bounceRate": "0"
    },
    {
        "pagePath": "/blog/2024/08/07/o-que-\u00e9-endere\u00e7amento-de-mem\u00f3ria/",
        "year": "2026",
        "month": "04",
        "activeUsers": "1",
        "screenPageViews": "2",
        "screenPageViewsPerSession": "2",
        "screenPageViewPerUser": "2",
        "averageSessionDuration": "321.18076",
        "bounceRate": "0"
    },
    {
        "pagePath": "/blog/2025/04/02/o-papel-de-uma-sre-em-sistemas-financeiros-cr\u00edticos/",
        "year": "2026",
        "month": "04",
        "activeUsers": "1",
        "screenPageViews": "1",
        "screenPageViewsPerSession": "1",
        "screenPageViewPerUser": "1",
        "averageSessionDuration": "5.362183",
        "bounceRate": "0"
    },
    {
        "pagePath": "/blog/2025/05/04/o-que-e-sfml",
        "year": "2026",
        "month": "04",
        "activeUsers": "1",
        "screenPageViews": "4",
        "screenPageViewsPerSession": "4",
        "screenPageViewPerUser": "4",
        "averageSessionDuration": "20.248965",
        "bounceRate": "0"
    },
    {
        "pagePath": "/blog/2025/08/18/o-que-e-o-git",
        "year": "2026",
        "month": "04",
        "activeUsers": "1",
        "screenPageViews": "2",
        "screenPageViewsPerSession": "2",
        "screenPageViewPerUser": "2",
        "averageSessionDuration": "5.849456",
        "bounceRate": "0"
    },
    {
        "pagePath": "/blog/2026/01/29/curso-de-gest\u00e3o-e-produtividade-com-danilo-mesquita/",
        "year": "2026",
        "month": "04",
        "activeUsers": "1",
        "screenPageViews": "1",
        "screenPageViewsPerSession": "1",
        "screenPageViewPerUser": "1",
        "averageSessionDuration": "0",
        "bounceRate": "0"
    },
    {
        "pagePath": "/blog/category",
        "year": "2026",
        "month": "04",
        "activeUsers": "1",
        "screenPageViews": "1",
        "screenPageViewsPerSession": "1",
        "screenPageViewPerUser": "1",
        "averageSessionDuration": "5.195349",
        "bounceRate": "1"
    },
    {
        "pagePath": "/blog/category/eventos",
        "year": "2026",
        "month": "04",
        "activeUsers": "1",
        "screenPageViews": "1",
        "screenPageViewsPerSession": "1",
        "screenPageViewPerUser": "1",
        "averageSessionDuration": "0",
        "bounceRate": "1"
    },
    {
        "pagePath": "/blog/category/gestao",
        "year": "2026",
        "month": "04",
        "activeUsers": "1",
        "screenPageViews": "1",
        "screenPageViewsPerSession": "1",
        "screenPageViewPerUser": "1",
        "averageSessionDuration": "5.024752",
        "bounceRate": "1"
    },
    {
        "pagePath": "/blog/category/projetos",
        "year": "2026",
        "month": "04",
        "activeUsers": "1",
        "screenPageViews": "1",
        "screenPageViewsPerSession": "1",
        "screenPageViewPerUser": "1",
        "averageSessionDuration": "1.640704",
        "bounceRate": "0"
    },
    {
        "pagePath": "/blog/page/2",
        "year": "2026",
        "month": "04",
        "activeUsers": "1",
        "screenPageViews": "1",
        "screenPageViewsPerSession": "1",
        "screenPageViewPerUser": "1",
        "averageSessionDuration": "0",
        "bounceRate": "1"
    },
    {
        "pagePath": "/c4p",
        "year": "2026",
        "month": "04",
        "activeUsers": "1",
        "screenPageViews": "1",
        "screenPageViewsPerSession": "1",
        "screenPageViewPerUser": "1",
        "averageSessionDuration": "100.548986",
        "bounceRate": "0"
    },
    {
        "pagePath": "/conduta",
        "year": "2026",
        "month": "04",
        "activeUsers": "1",
        "screenPageViews": "1",
        "screenPageViewsPerSession": "1",
        "screenPageViewPerUser": "1",
        "averageSessionDuration": "0.435188",
        "bounceRate": "0"
    },
    {
        "pagePath": "/contact",
        "year": "2026",
        "month": "04",
        "activeUsers": "1",
        "screenPageViews": "1",
        "screenPageViewsPerSession": "1",
        "screenPageViewPerUser": "1",
        "averageSessionDuration": "0.599853",
        "bounceRate": "0"
    },
    {
        "pagePath": "/participe/estudar/",
        "year": "2026",
        "month": "04",
        "activeUsers": "1",
        "screenPageViews": "3",
        "screenPageViewsPerSession": "1",
        "screenPageViewPerUser": "3",
        "averageSessionDuration": "520.32955066666671",
        "bounceRate": "0.66666666666666663"
    },
    {
        "pagePath": "/previews/pr-`",
        "year": "2026",
        "month": "04",
        "activeUsers": "1",
        "screenPageViews": "1",
        "screenPageViewsPerSession": "1",
        "screenPageViewPerUser": "1",
        "averageSessionDuration": "5.700381",
        "bounceRate": "1"
    },
    {
        "pagePath": "/quero/apoiar",
        "year": "2026",
        "month": "04",
        "activeUsers": "1",
        "screenPageViews": "1",
        "screenPageViewsPerSession": "1",
        "screenPageViewPerUser": "1",
        "averageSessionDuration": "220.242848",
        "bounceRate": "0"
    },
    {
        "pagePath": "/quero/esu",
        "year": "2026",
        "month": "04",
        "activeUsers": "1",
        "screenPageViews": "1",
        "screenPageViewsPerSession": "1",
        "screenPageViewPerUser": "1",
        "averageSessionDuration": "5.665227",
        "bounceRate": "1"
    },
    {
        "pagePath": "/reembolso",
        "year": "2026",
        "month": "04",
        "activeUsers": "1",
        "screenPageViews": "1",
        "screenPageViewsPerSession": "1",
        "screenPageViewPerUser": "1",
        "averageSessionDuration": "6.642547",
        "bounceRate": "0"
    },
    {
        "pagePath": "/reenbolso",
        "year": "2026",
        "month": "04",
        "activeUsers": "1",
        "screenPageViews": "1",
        "screenPageViewsPerSession": "1",
        "screenPageViewPerUser": "1",
        "averageSessionDuration": "5.056129",
        "bounceRate": "0"
    },
    {
        "pagePath": "/regex",
        "year": "2026",
        "month": "04",
        "activeUsers": "1",
        "screenPageViews": "1",
        "screenPageViewsPerSession": "1",
        "screenPageViewPerUser": "1",
        "averageSessionDuration": "5.317382",
        "bounceRate": "1"
    },
    {
        "pagePath": "/trilhas/github-starter/",
        "year": "2026",
        "month": "04",
        "activeUsers": "1",
        "screenPageViews": "1",
        "screenPageViewsPerSession": "1",
        "screenPageViewPerUser": "1",
        "averageSessionDuration": "1.852651",
        "bounceRate": "1"
    },
    {
        "pagePath": "/trilhas/github/page-7/",
        "year": "2026",
        "month": "04",
        "activeUsers": "1",
        "screenPageViews": "1",
        "screenPageViewsPerSession": "1",
        "screenPageViewPerUser": "1",
        "averageSessionDuration": "4.390793",
        "bounceRate": "1"
    },
    {
        "pagePath": "/trilhas/intro",
        "year": "2026",
        "month": "04",
        "activeUsers": "1",
        "screenPageViews": "1",
        "screenPageViewsPerSession": "1",
        "screenPageViewPerUser": "1",
        "averageSessionDuration": "4.441918",
        "bounceRate": "0"
    },
    {
        "pagePath": "/trilhas/python/page-7/",
        "year": "2026",
        "month": "04",
        "activeUsers": "1",
        "screenPageViews": "1",
        "screenPageViewsPerSession": "1",
        "screenPageViewPerUser": "1",
        "averageSessionDuration": "1.842691",
        "bounceRate": "1"
    },
    {
        "pagePath": "/blog/2026/03/30/curso-introducao-python/",
        "year": "2026",
        "month": "04",
        "activeUsers": "0",
        "screenPageViews": "1",
        "screenPageViewsPerSession": "1",
        "screenPageViewPerUser": "0",
        "averageSessionDuration": "0",
        "bounceRate": "1"
    },
    {
        "pagePath": "/trilhas/github/page-3/",
        "year": "2026",
        "month": "04",
        "activeUsers": "0",
        "screenPageViews": "2",
        "screenPageViewsPerSession": "1",
        "screenPageViewPerUser": "0",
        "averageSessionDuration": "0",
        "bounceRate": "1"
    }
]